LICENSE.txt
LICENSES_bundled.txt
MANIFEST.in
Makefile
README.md
pyproject.toml
requirements-dev.txt
requirements.txt
setup.cfg
setup.py
mrrt/__init__.py
mrrt.mri.egg-info/PKG-INFO
mrrt.mri.egg-info/SOURCES.txt
mrrt.mri.egg-info/dependency_links.txt
mrrt.mri.egg-info/requires.txt
mrrt.mri.egg-info/top_level.txt
mrrt/mri/__init__.py
mrrt/mri/_density_compensation.py
mrrt/mri/_partial_fourier.py
mrrt/mri/_unwrap.py
mrrt/mri/version.py
mrrt/mri/coils/__init__.py
mrrt/mri/coils/_bias.py
mrrt/mri/coils/_coil_maps.py
mrrt/mri/coils/_coil_pca.py
mrrt/mri/coils/_prewhiten.py
mrrt/mri/coils/tests/test_prewhiten.py
mrrt/mri/data/all_Rfull_4096_VPR5_MULTICLASS.mat
mrrt/mri/data/multiecho_radial_traj.npz
mrrt/mri/data/mytrajmeas_VPR5_1shot.mat
mrrt/mri/data/wi2_VPR5_1shot.mat
mrrt/mri/field_maps/__init__.py
mrrt/mri/field_maps/_mri_exp_approx.py
mrrt/mri/field_maps/_mri_exp_mult.py
mrrt/mri/field_maps/tests/_bench.py
mrrt/mri/field_maps/tests/test_mri_exp_approx.py
mrrt/mri/field_maps/tests/test_mri_exp_mult.py
mrrt/mri/operators/_MRI.py
mrrt/mri/operators/_MRI_Cartesian.py
mrrt/mri/operators/_NUFFT.py
mrrt/mri/operators/__init__.py
mrrt/mri/operators/_pixel_basis.py
mrrt/mri/operators/fat_models.py
mrrt/mri/operators/linear_operator_notes.txt
mrrt/mri/operators/bench/__init__.py
mrrt/mri/operators/bench/bench_mri.py
mrrt/mri/operators/bench/bench_subset.py
mrrt/mri/operators/bench/example_debug.py
mrrt/mri/operators/bench/line_prof.py
mrrt/mri/operators/tests/__init__.py
mrrt/mri/operators/tests/_generate_testdata.py
mrrt/mri/operators/tests/test_mri_cartesian.py
mrrt/mri/operators/tests/test_mri_noncartesian.py
mrrt/mri/operators/tests/test_pixel_basis.py
mrrt/mri/sim/__init__.py
mrrt/mri/sim/_mri_fmap_sim.py
mrrt/mri/sim/_mri_objects.py
mrrt/mri/sim/_mri_sensemap_sim.py
mrrt/mri/sim/tests/test_objects.py
mrrt/mri/sim/tests/test_sensemap.py
mrrt/mri/tests/test_partial_fourier.py